{
    "ip": "10.10.90.27",
    "port": 59336,
    "chor_port": 59334,
    "Blik_time": {
        "HZ": 1
    },
    "adr_time": {
        "1": 0,
        "2": 0,
        "3": 0,
        "4": 0
    },
    "anchor_cfg": {
        "afffffffffffff01": [
            10,
            50,
            0
        ],
        "afffffffffffff02": [
            10,
            50,
            0
        ],
        "afffffffffffff03": [
            10,
            50,
            0
        ],
        "afffffffffffff04": [
            10,
            50,
            0
        ]
    },
    "Tag_Addr_XYZ": {
        "a100000000000001": [
            9,
            70,
            0
        ],
        "a100000000000002": [
            79,
            9,
            0
        ],
        "a100000000000003": [
            23,
            99,
            0
        ],
        "a100000000000004": [
            76,
            78,
            0
        ],
        "a100000000000005": [
            46,
            30,
            0
        ],
        "a100000000000006": [
            52,
            25,
            0
        ],
        "a100000000000007": [
            38,
            95,
            0
        ],
        "a100000000000008": [
            32,
            12,
            0
        ],
        "a100000000000009": [
            26,
            18,
            0
        ],
        "a100000000000010": [
            44,
            0,
            0
        ]
    }
}